pygalaga/__init__.py
pygalaga/assets/explosion.gif
pygalaga/assets/missile.png
pygalaga/assets/ship.png
pygalaga/assets/sounds/bomb.ogg
pygalaga/assets/sounds/explosion.mp3
pygalaga/assets/sounds/shoot.mp3
pygalaga/assets/space_invader_red.png
pygalaga/components/__init__.py
pygalaga/components/aliens.py
pygalaga/components/bullet.py
pygalaga/components/ship.py
pygalaga/components/sounds.py
pygalaga/config.py
pygalaga/game.py
pygalaga/utils.py
pygalaga-1.0.5.dist-info/LICENSE
pygalaga-1.0.5.dist-info/METADATA
pygalaga-1.0.5.dist-info/WHEEL
pygalaga-1.0.5.dist-info/entry_points.txt
pygalaga-1.0.5.dist-info/RECORD
