Metadata-Version: 2.3
Name: pygalaga
Version: 1.0.5
Summary: A simple Galaga clone using Pygame
License: MIT
Author: Abhishek Prakash
Author-email: abhishek.g.prakash@gmail.com
Requires-Python: >=3.10,<4.0
Classifier: License :: OSI Approved :: MIT License
Classifier: Programming Language :: Python :: 3
Classifier: Programming Language :: Python :: 3.10
Classifier: Programming Language :: Python :: 3.11
Classifier: Programming Language :: Python :: 3.12
Classifier: Programming Language :: Python :: 3.13
Requires-Dist: pillow (>=10.4.0,<11.0.0)
Requires-Dist: pygame (>=2.5.0,<3.0.0)
